{
    "customer_email": "malav.shah@juspay.in",
    "customer_phone": "7076607677",
    "customer_id": "7076607677",
    "status_id": 23,
    "status": "PENDING_VBV",
    "id": "ordeh_9251b30c102b43c9bf841280bf319d3b",
    "merchant_id": "merchant_success",
    "amount": 1,
    "currency": "INR",
    "order_id": "test_1692937996",
    "date_created": "2023-08-25T04:33:16Z",
    "return_url": "https://google.com",
    "product_id": "Shocks",
    "payment_links": {
    "iframe": "https://sandbox.juspay.in/orders/ordeh_9251b30c102b43c9bf841280bf319d3b/payment-page",
    "web": "https://sandbox.juspay.in/orders/ordeh_9251b30c102b43c9bf841280bf319d3b/payment-page",
    "mobile": "https://sandbox.juspay.in/orders/ordeh_9251b30c102b43c9bf841280bf319d3b/payment-page"
    },
    "udf1": "",
    "udf2": "",
    "udf3": "",
    "udf4": "",
    "udf5": "",
    "udf6": "",
    "udf7": "",
    "udf8": "",
    "udf9": "",
    "udf10": "",
    "txn_id": "ms-test_1692937996-1",
    "payment_method_type": "CARD",
    "auth_type": "THREE_DS",
    "card": {
    "expiry_year": "2029",
    "card_reference": "",
    "saved_to_locker": false,
    "expiry_month": "04",
    "name_on_card": "Rahul Agarwal",
    "card_issuer": "ICICI Bank",
    "last_four_digits": "7823",
    "using_saved_card": false,
    "card_fingerprint": "6tp38u4hforepdacermdhlcfkd",
    "card_isin": "516640",
    "card_type": "DEBIT",
    "card_brand": "MASTERCARD",
    "using_token": false,
    "tokens": [],
    "card_issuer_country": "INDIA",
    "juspay_bank_code": "JP_ICICI",
    "extended_card_type": "MASTERCARD",
    "payment_account_reference": ""
    },
    "payment_method": "MASTERCARD",
    "refunded": false,
    "amount_refunded": 0,
    "effective_amount": 1,
    "resp_code": null,
    "resp_message": null,
    "bank_error_code": "",
    "bank_error_message": "",
    "txn_uuid": "mozbQSyAuwW3kWjvNgH",
    "txn_detail": {
    "txn_id": "ms-test_1692937996-1",
    "order_id": "test_1692937996",
    "status": "PENDING_VBV",
    "error_code": null,
    "net_amount": 1,
    "surcharge_amount": 0,
    "tax_amount": 0,
    "txn_amount": 1,
    "offer_deduction_amount": null,
    "gateway_id": 23,
    "currency": "INR",
    "express_checkout": false,
    "redirect": true,
    "txn_uuid": "mozbQSyAuwW3kWjvNgH",
    "gateway": "RAZORPAY",
    "error_message": "",
    "created": "2023-08-25T04:33:23Z",
    "txn_flow_type": "CARD_TRANSACTION"
    },
    "gateway_id": 23,
    "metadata": {
    "payment_links": {
    "iframe": "https://sandbox.juspay.in/orders/ordeh_9251b30c102b43c9bf841280bf319d3b/payment-page",
    "web": "https://sandbox.juspay.in/orders/ordeh_9251b30c102b43c9bf841280bf319d3b/payment-page",
    "mobile": "https://sandbox.juspay.in/orders/ordeh_9251b30c102b43c9bf841280bf319d3b/payment-page"
    },
    "payment_page_client_id": "defaultclient"
    },
    "gateway_reference_id": null,
    "offers": []
    }